{
    "category": "redstone",
    "type": "minecraft:crafting_shaped",
    "pattern": [
        "##",
        "Di",
        "##"
    ],
    "key": {
        "#": {
            "tag": "minecraft:dark_oak_logs"
        },
        "D": {
            "item": "minecraft:dark_oak_planks"
        },
        "i": {
            "item": "minecraft:iron_ingot"
        }
    },
    "result": {
        "item": "minecraft:dark_oak_door",
        "count": 1
    },
    "show_notification": true,
    "group": "Door"
}