{
    "category": "redstone",
    "type": "minecraft:crafting_shaped",
    "pattern": [
        "i",
        "/",
        "O"
    ],
    "key": {
        "i": {
            "item": "minecraft:iron_ingot"
        },
        "/": {
            "item": "minecraft:stick"
        },
        "O": {
            "tag": "minecraft:planks"
        }
    },
    "result": {
        "item": "minecraft:tripwire_hook",
        "count": 1
    },
    "show_notification": "true",
    "group": "Redstone Components"
}